[
    {
        "data": [
            {
                "allowDdcCi": true,
                "allowSdrSoftwareBrightness": false,
                "autoRotation": "InTabletMode",
                "brightness": 0.9725490196078431,
                "colorPowerTradeoff": "PreferEfficiency",
                "colorProfileSource": "sRGB",
                "connectorName": "DVI-I-1",
                "detectedDdcCi": true,
                "edidHash": "9bab8b93fa48d44abcbd92b2885d0755",
                "edidIdentifier": "HWP 10584 0 48 2012 0",
                "edrPolicy": "always",
                "highDynamicRange": false,
                "iccProfilePath": "",
                "maxBitsPerColor": 0,
                "mode": {
                    "height": 1440,
                    "refreshRate": 59951,
                    "width": 2560
                },
                "overscan": 0,
                "rgbRange": "Automatic",
                "scale": 1.15,
                "sdrBrightness": 200,
                "sdrGamutWideness": 0,
                "transform": "Normal",
                "uuid": "88fa6ccf-ba18-4076-81fd-326dd15c371d",
                "vrrPolicy": "Automatic",
                "wideColorGamut": false
            },
            {
                "allowSdrSoftwareBrightness": true,
                "autoRotation": "InTabletMode",
                "brightness": 1,
                "colorPowerTradeoff": "PreferEfficiency",
                "colorProfileSource": "sRGB",
                "connectorName": "Unknown-1",
                "highDynamicRange": false,
                "iccProfilePath": "",
                "mode": {
                    "height": 1440,
                    "refreshRate": 60000,
                    "width": 2560
                },
                "overscan": 0,
                "rgbRange": "Automatic",
                "scale": 1,
                "sdrBrightness": 200,
                "sdrGamutWideness": 0,
                "transform": "Normal",
                "vrrPolicy": "Automatic",
                "wideColorGamut": false
            }
        ],
        "name": "outputs"
    },
    {
        "data": [
            {
                "lidClosed": false,
                "outputs": [
                    {
                        "enabled": true,
                        "outputIndex": 0,
                        "position": {
                            "x": 0,
                            "y": 0
                        },
                        "priority": 0,
                        "replicationSource": ""
                    }
                ]
            },
            {
                "lidClosed": false,
                "outputs": [
                    {
                        "enabled": true,
                        "outputIndex": 1,
                        "position": {
                            "x": 0,
                            "y": 0
                        },
                        "priority": 0,
                        "replicationSource": ""
                    }
                ]
            }
        ],
        "name": "setups"
    }
]
